setup.py
pass_manager.egg-info/PKG-INFO
pass_manager.egg-info/SOURCES.txt
pass_manager.egg-info/dependency_links.txt
pass_manager.egg-info/entry_points.txt
pass_manager.egg-info/not-zip-safe
pass_manager.egg-info/requires.txt
pass_manager.egg-info/top_level.txt
src/__init__.py
src/encrypter.py
src/pass_manager.py