Metadata-Version: 1.1
Name: pass-manager
Version: 1.1.0
Summary: Simple CLI Password Manager
Home-page: https://github.com/petitviolet/pass-manager
Author: petitviolet
Author-email: violethero0820@gmail.com
License: MIT
Platform: Mac OS X
Classifier: Environment :: Console
Classifier: Intended Audience :: Developers
Classifier: Operating System :: OS Independent
Classifier: Programming Language :: Python
Classifier: Topic :: Utilities
